binary_system/__init__.py
binary_system/function.py
binary_system-0.0.1.dist-info/METADATA
binary_system-0.0.1.dist-info/WHEEL
binary_system-0.0.1.dist-info/top_level.txt
binary_system-0.0.1.dist-info/RECORD
