Metadata-Version: 2.1
Name: binary-system
Version: 0.0.1
Summary: UNKNOWN
Home-page: https://github.com/fcoagz/code-binary-system
Author: Francisco Griman
Author-email: grihardware@gmail.com
License: MIT
Platform: UNKNOWN
Classifier: Intended Audience :: Developers
Classifier: License :: OSI Approved :: MIT License
Classifier: Programming Language :: Python :: 3
Classifier: Programming Language :: Python :: 3.7
Classifier: Programming Language :: Python :: 3.8
Classifier: Programming Language :: Python :: 3.10
